{"id": "ZTpDh-HmwNs", "title": "Def Con Dos - Veraneo en Puerto Hurraco", "formats": [{"asr": 48000, "filesize": 1474268, "format_id": "249", "format_note": "tiny", "fps": null, "height": null, "quality": 0, "tbr": 47.788, "url": "https://rr1---sn-0opoxu-ihv6.googlevideo.com/videoplayback?expire=1670792375&ei=V_CVY-GTJs30kgaIy77oAg&ip=189.173.225.87&id=o-ANG1Pd-KLSbUrtYD-H6LMaMC4kR5u3RaRXeLAZHbh5e-&itag=249&source=youtube&requiressl=yes&mh=XG&mm=31%2C29&mn=sn-0opoxu-ihv6%2Csn-q4fl6ns7&ms=au%2Crdu&mv=m&mvi=1&pl=24&initcwndbps=938750&vprv=1&mime=audio%2Fwebm&ns=dzQ4g6pkTsEjvnvwUg8PhYQJ&gir=yes&clen=1474268&dur=246.801&lmt=1573105859617709&mt=1670770639&fvip=5&keepalive=yes&fexp=24001373%2C24007246&c=WEB&txp=1311222&n=Rp0Vrw8keBl_1-3xr&sparams=expire%2Cei%2Cip%2Cid%2Citag%2Csource%2Crequiressl%2Cvprv%2Cmime%2Cns%2Cgir%2Cclen%2Cdur%2Clmt&lsparams=mh%2Cmm%2Cmn%2Cms%2Cmv%2Cmvi%2Cpl%2Cinitcwndbps&lsig=AG3C_xAwRAIgVh1R5eiD0DmC3AoBHYZVMlx0x8cnzl44upmesSZ1gpcCIDPZetc-1ip7Gv-czGl9JOJu3-GTMe8pKaMoFD414tr5&sig=AOq0QJ8wRAIgZxAF3gCcnS-lJRKclqqbkHis2MTCH8rk-Yh80ruKSukCIGlWHFGFBzH5VEY7qu_riNcXZcilBJ69DSchHjc4p-ue", "width": null, "ext": "webm", "vcodec": "none", "acodec": "opus", "abr": 47.788, "downloader_options": {"http_chunk_size": 10485760}, "container": "webm_dash", "format": "249 - audio only (tiny)", "protocol": "https", "http_headers": {"User-Agent": "Mozilla/5.0 (Windows NT 10.0; Win64; x64) AppleWebKit/537.36 (KHTML, like Gecko) Chrome/72.0.3620.0 Safari/537.36", "Accept-Charset": "ISO-8859-1,utf-8;q=0.7,*;q=0.7", "Accept": "text/html,application/xhtml+xml,application/xml;q=0.9,*/*;q=0.8", "Accept-Encoding": "gzip, deflate", "Accept-Language": "en-us,en;q=0.5"}}, {"asr": 48000, "filesize": 1924575, "format_id": "250", "format_note": "tiny", "fps": null, "height": null, "quality": 0, "tbr": 62.384, "url": "https://rr1---sn-0opoxu-ihv6.googlevideo.com/videoplayback?expire=1670792375&ei=V_CVY-GTJs30kgaIy77oAg&ip=189.173.225.87&id=o-ANG1Pd-KLSbUrtYD-H6LMaMC4kR5u3RaRXeLAZHbh5e-&itag=250&source=youtube&requiressl=yes&mh=XG&mm=31%2C29&mn=sn-0opoxu-ihv6%2Csn-q4fl6ns7&ms=au%2Crdu&mv=m&mvi=1&pl=24&initcwndbps=938750&vprv=1&mime=audio%2Fwebm&ns=dzQ4g6pkTsEjvnvwUg8PhYQJ&gir=yes&clen=1924575&dur=246.801&lmt=1573105896205373&mt=1670770639&fvip=5&keepalive=yes&fexp=24001373%2C24007246&c=WEB&txp=1311222&n=Rp0Vrw8keBl_1-3xr&sparams=expire%2Cei%2Cip%2Cid%2Citag%2Csource%2Crequiressl%2Cvprv%2Cmime%2Cns%2Cgir%2Cclen%2Cdur%2Clmt&lsparams=mh%2Cmm%2Cmn%2Cms%2Cmv%2Cmvi%2Cpl%2Cinitcwndbps&lsig=AG3C_xAwRAIgdjc1LZTHtgPD8mwZRPG8suWP7rTu8tKLwWI1DMgZ3PICIHl7HPpC5nwSyvy4NpO8P9d6TVH_fbOjieKcMiOBSqe1&sig=AOq0QJ8wRQIgSvgCHOXV3tSXBxwEkbl5v68IGmzKa_CrPz-H4XTqvvcCIQDaCOAXnZdLhBEvIV6oXPUCZEYOxO1EYwvxubGJ5ZSxnw==", "width": null, "ext": "webm", "vcodec": "none", "acodec": "opus", "abr": 62.384, "downloader_options": {"http_chunk_size": 10485760}, "container": "webm_dash", "format": "250 - audio only (tiny)", "protocol": "https", "http_headers": {"User-Agent": "Mozilla/5.0 (Windows NT 10.0; Win64; x64) AppleWebKit/537.36 (KHTML, like Gecko) Chrome/72.0.3620.0 Safari/537.36", "Accept-Charset": "ISO-8859-1,utf-8;q=0.7,*;q=0.7", "Accept": "text/html,application/xhtml+xml,application/xml;q=0.9,*/*;q=0.8", "Accept-Encoding": "gzip, deflate", "Accept-Language": "en-us,en;q=0.5"}}, {"asr": 48000, "filesize": 3784103, "format_id": "251", "format_note": "tiny", "fps": null, "height": null, "quality": 0, "tbr": 122.66, "url": "https://rr1---sn-0opoxu-ihv6.googlevideo.com/videoplayback?expire=1670792375&ei=V_CVY-GTJs30kgaIy77oAg&ip=189.173.225.87&id=o-ANG1Pd-KLSbUrtYD-H6LMaMC4kR5u3RaRXeLAZHbh5e-&itag=251&source=youtube&requiressl=yes&mh=XG&mm=31%2C29&mn=sn-0opoxu-ihv6%2Csn-q4fl6ns7&ms=au%2Crdu&mv=m&mvi=1&pl=24&initcwndbps=938750&vprv=1&mime=audio%2Fwebm&ns=dzQ4g6pkTsEjvnvwUg8PhYQJ&gir=yes&clen=3784103&dur=246.801&lmt=1573105859908767&mt=1670770639&fvip=5&keepalive=yes&fexp=24001373%2C24007246&c=WEB&txp=1311222&n=Rp0Vrw8keBl_1-3xr&sparams=expire%2Cei%2Cip%2Cid%2Citag%2Csource%2Crequiressl%2Cvprv%2Cmime%2Cns%2Cgir%2Cclen%2Cdur%2Clmt&lsparams=mh%2Cmm%2Cmn%2Cms%2Cmv%2Cmvi%2Cpl%2Cinitcwndbps&lsig=AG3C_xAwRQIhAO2olC_oflMo1tm0IAb4UQVQCzMB898_LFk1mDpymcgZAiBBwaMOdurRsWFoJxfMnj9yb5bhCFK25Z52T9VlNG8JtA%3D%3D&sig=AOq0QJ8wRAIfPqUrS2-ZnWLneG_A8Sjz_6PXq16YASy0za_QKeDIDAIhANMXOV2fUEO9hBEFkdQ5OeYGPo3gLnLt-GWhdTlyLkmD", "width": null, "ext": "webm", "vcodec": "none", "acodec": "opus", "abr": 122.66, "downloader_options": {"http_chunk_size": 10485760}, "container": "webm_dash", "format": "251 - audio only (tiny)", "protocol": "https", "http_headers": {"User-Agent": "Mozilla/5.0 (Windows NT 10.0; Win64; x64) AppleWebKit/537.36 (KHTML, like Gecko) Chrome/72.0.3620.0 Safari/537.36", "Accept-Charset": "ISO-8859-1,utf-8;q=0.7,*;q=0.7", "Accept": "text/html,application/xhtml+xml,application/xml;q=0.9,*/*;q=0.8", "Accept-Encoding": "gzip, deflate", "Accept-Language": "en-us,en;q=0.5"}}, {"asr": 44100, "filesize": 3995881, "format_id": "140", "format_note": "tiny", "fps": null, "height": null, "quality": 0, "tbr": 129.499, "url": "https://rr1---sn-0opoxu-ihv6.googlevideo.com/videoplayback?expire=1670792375&ei=V_CVY-GTJs30kgaIy77oAg&ip=189.173.225.87&id=o-ANG1Pd-KLSbUrtYD-H6LMaMC4kR5u3RaRXeLAZHbh5e-&itag=140&source=youtube&requiressl=yes&mh=XG&mm=31%2C29&mn=sn-0opoxu-ihv6%2Csn-q4fl6ns7&ms=au%2Crdu&mv=m&mvi=1&pl=24&initcwndbps=938750&vprv=1&mime=audio%2Fmp4&ns=dzQ4g6pkTsEjvnvwUg8PhYQJ&gir=yes&clen=3995881&dur=246.851&lmt=1573105979974596&mt=1670770639&fvip=5&keepalive=yes&fexp=24001373%2C24007246&c=WEB&txp=1311222&n=Rp0Vrw8keBl_1-3xr&sparams=expire%2Cei%2Cip%2Cid%2Citag%2Csource%2Crequiressl%2Cvprv%2Cmime%2Cns%2Cgir%2Cclen%2Cdur%2Clmt&lsparams=mh%2Cmm%2Cmn%2Cms%2Cmv%2Cmvi%2Cpl%2Cinitcwndbps&lsig=AG3C_xAwRgIhAJXaBnSlTbtex8oZlVF6603UpYJMmT5WUaSaiG6m-SgDAiEAvRoDGjlwnzSUJA3gjC2tyKMxEaJ0m3TklO4C5m7WRHM%3D&sig=AOq0QJ8wRQIhAOn0Ap00lMlCOnI5T-FJDUouQuW2ynt1r6EbfmYJM2YBAiAP6eOr2IwMayUSnDuU7m_U2Vi0ALSX6nnsMKZNObPjgA==", "width": null, "ext": "m4a", "vcodec": "none", "acodec": "mp4a.40.2", "abr": 129.499, "downloader_options": {"http_chunk_size": 10485760}, "container": "m4a_dash", "format": "140 - audio only (tiny)", "protocol": "https", "http_headers": {"User-Agent": "Mozilla/5.0 (Windows NT 10.0; Win64; x64) AppleWebKit/537.36 (KHTML, like Gecko) Chrome/72.0.3620.0 Safari/537.36", "Accept-Charset": "ISO-8859-1,utf-8;q=0.7,*;q=0.7", "Accept": "text/html,application/xhtml+xml,application/xml;q=0.9,*/*;q=0.8", "Accept-Encoding": "gzip, deflate", "Accept-Language": "en-us,en;q=0.5"}}, {"asr": null, "filesize": 750353, "format_id": "160", "format_note": "144p", "fps": 25, "height": 144, "quality": 0, "tbr": 24.33, "url": "https://rr1---sn-0opoxu-ihv6.googlevideo.com/videoplayback?expire=1670792375&ei=V_CVY-GTJs30kgaIy77oAg&ip=189.173.225.87&id=o-ANG1Pd-KLSbUrtYD-H6LMaMC4kR5u3RaRXeLAZHbh5e-&itag=160&aitags=133%2C134%2C135%2C160%2C242%2C243%2C244%2C278&source=youtube&requiressl=yes&mh=XG&mm=31%2C29&mn=sn-0opoxu-ihv6%2Csn-q4fl6ns7&ms=au%2Crdu&mv=m&mvi=1&pl=24&initcwndbps=938750&vprv=1&mime=video%2Fmp4&ns=dzQ4g6pkTsEjvnvwUg8PhYQJ&gir=yes&clen=750353&dur=246.720&lmt=1573105993479975&mt=1670770639&fvip=5&keepalive=yes&fexp=24001373%2C24007246&c=WEB&txp=1316222&n=Rp0Vrw8keBl_1-3xr&sparams=expire%2Cei%2Cip%2Cid%2Caitags%2Csource%2Crequiressl%2Cvprv%2Cmime%2Cns%2Cgir%2Cclen%2Cdur%2Clmt&lsparams=mh%2Cmm%2Cmn%2Cms%2Cmv%2Cmvi%2Cpl%2Cinitcwndbps&lsig=AG3C_xAwRAIgbdmwmbhTP5eUI8lo8_71bJt6AVoJ5rQUbKZ_nYYMGJMCIHLBjKAVuPzeLMsme_KDxYPIjuW_NtIWqjiEJRhTodgg&sig=AOq0QJ8wRQIgTVrTSQYN47cwmi0qiUisaw1gp2ERZn-mpV1chPCVwLICIQCDru-nH3iMs5oqYjJveO_K7JgoPrnARL7-CnRGjrA8IQ==", "width": 192, "ext": "mp4", "vcodec": "avc1.4d400b", "acodec": "none", "vbr": 24.33, "downloader_options": {"http_chunk_size": 10485760}, "container": "mp4_dash", "format": "160 - 192x144 (144p)", "protocol": "https", "http_headers": {"User-Agent": "Mozilla/5.0 (Windows NT 10.0; Win64; x64) AppleWebKit/537.36 (KHTML, like Gecko) Chrome/72.0.3620.0 Safari/537.36", "Accept-Charset": "ISO-8859-1,utf-8;q=0.7,*;q=0.7", "Accept": "text/html,application/xhtml+xml,application/xml;q=0.9,*/*;q=0.8", "Accept-Encoding": "gzip, deflate", "Accept-Language": "en-us,en;q=0.5"}}, {"asr": null, "filesize": 864639, "format_id": "278", "format_note": "144p", "fps": 25, "height": 144, "quality": 0, "tbr": 28.036, "url": "https://rr1---sn-0opoxu-ihv6.googlevideo.com/videoplayback?expire=1670792375&ei=V_CVY-GTJs30kgaIy77oAg&ip=189.173.225.87&id=o-ANG1Pd-KLSbUrtYD-H6LMaMC4kR5u3RaRXeLAZHbh5e-&itag=278&aitags=133%2C134%2C135%2C160%2C242%2C243%2C244%2C278&source=youtube&requiressl=yes&mh=XG&mm=31%2C29&mn=sn-0opoxu-ihv6%2Csn-q4fl6ns7&ms=au%2Crdu&mv=m&mvi=1&pl=24&initcwndbps=938750&vprv=1&mime=video%2Fwebm&ns=dzQ4g6pkTsEjvnvwUg8PhYQJ&gir=yes&clen=864639&dur=246.720&lmt=1573105995342660&mt=1670770639&fvip=5&keepalive=yes&fexp=24001373%2C24007246&c=WEB&txp=1316222&n=Rp0Vrw8keBl_1-3xr&sparams=expire%2Cei%2Cip%2Cid%2Caitags%2Csource%2Crequiressl%2Cvprv%2Cmime%2Cns%2Cgir%2Cclen%2Cdur%2Clmt&lsparams=mh%2Cmm%2Cmn%2Cms%2Cmv%2Cmvi%2Cpl%2Cinitcwndbps&lsig=AG3C_xAwRAIgY6c32DRiEJyHVy2FjRnSItj-OQzyzHRQIVy5IQbr6FICIDATmlL-zHghJ59DtFM-WYY_cRYvBc0eBQYQgOIu-Mdj&sig=AOq0QJ8wRAIgZhVg96IMA7bavjGyyMfqEtnOP0DSF4VVrcpcfBPBHXoCICho6bTXziVHKW6yRGPhLimPj1Y-gkp3kImr91YAyo8T", "width": 192, "ext": "webm", "vcodec": "vp9", "acodec": "none", "vbr": 28.036, "downloader_options": {"http_chunk_size": 10485760}, "container": "webm_dash", "format": "278 - 192x144 (144p)", "protocol": "https", "http_headers": {"User-Agent": "Mozilla/5.0 (Windows NT 10.0; Win64; x64) AppleWebKit/537.36 (KHTML, like Gecko) Chrome/72.0.3620.0 Safari/537.36", "Accept-Charset": "ISO-8859-1,utf-8;q=0.7,*;q=0.7", "Accept": "text/html,application/xhtml+xml,application/xml;q=0.9,*/*;q=0.8", "Accept-Encoding": "gzip, deflate", "Accept-Language": "en-us,en;q=0.5"}}, {"asr": null, "filesize": 1466133, "format_id": "133", "format_note": "240p", "fps": 25, "height": 240, "quality": 1, "tbr": 47.539, "url": "https://rr1---sn-0opoxu-ihv6.googlevideo.com/videoplayback?expire=1670792375&ei=V_CVY-GTJs30kgaIy77oAg&ip=189.173.225.87&id=o-ANG1Pd-KLSbUrtYD-H6LMaMC4kR5u3RaRXeLAZHbh5e-&itag=133&aitags=133%2C134%2C135%2C160%2C242%2C243%2C244%2C278&source=youtube&requiressl=yes&mh=XG&mm=31%2C29&mn=sn-0opoxu-ihv6%2Csn-q4fl6ns7&ms=au%2Crdu&mv=m&mvi=1&pl=24&initcwndbps=938750&vprv=1&mime=video%2Fmp4&ns=dzQ4g6pkTsEjvnvwUg8PhYQJ&gir=yes&clen=1466133&dur=246.720&lmt=1573105993423077&mt=1670770639&fvip=5&keepalive=yes&fexp=24001373%2C24007246&c=WEB&txp=1316222&n=Rp0Vrw8keBl_1-3xr&sparams=expire%2Cei%2Cip%2Cid%2Caitags%2Csource%2Crequiressl%2Cvprv%2Cmime%2Cns%2Cgir%2Cclen%2Cdur%2Clmt&lsparams=mh%2Cmm%2Cmn%2Cms%2Cmv%2Cmvi%2Cpl%2Cinitcwndbps&lsig=AG3C_xAwRAIge_bnHyhU6HoQJNzncbxFGjbtYA_nYqQIYwJsQbJ8wMkCIFjQ6YrVNuxI7Ku1gJD6aFJ6dQi4iqv4sULzO-FuyWRm&sig=AOq0QJ8wRAIgWGhBfa94mZVrGcf6JulTPPojcPulCJI9yyAxJxIS8EACIFlwEdyU0QcQQQnGj0P0cIN0zj6feyjVB1ZFrtNGPno2", "width": 320, "ext": "mp4", "vcodec": "avc1.4d400d", "acodec": "none", "vbr": 47.539, "downloader_options": {"http_chunk_size": 10485760}, "container": "mp4_dash", "format": "133 - 320x240 (240p)", "protocol": "https", "http_headers": {"User-Agent": "Mozilla/5.0 (Windows NT 10.0; Win64; x64) AppleWebKit/537.36 (KHTML, like Gecko) Chrome/72.0.3620.0 Safari/537.36", "Accept-Charset": "ISO-8859-1,utf-8;q=0.7,*;q=0.7", "Accept": "text/html,application/xhtml+xml,application/xml;q=0.9,*/*;q=0.8", "Accept-Encoding": "gzip, deflate", "Accept-Language": "en-us,en;q=0.5"}}, {"asr": null, "filesize": 1495450, "format_id": "242", "format_note": "240p", "fps": 25, "height": 240, "quality": 1, "tbr": 48.49, "url": "https://rr1---sn-0opoxu-ihv6.googlevideo.com/videoplayback?expire=1670792375&ei=V_CVY-GTJs30kgaIy77oAg&ip=189.173.225.87&id=o-ANG1Pd-KLSbUrtYD-H6LMaMC4kR5u3RaRXeLAZHbh5e-&itag=242&aitags=133%2C134%2C135%2C160%2C242%2C243%2C244%2C278&source=youtube&requiressl=yes&mh=XG&mm=31%2C29&mn=sn-0opoxu-ihv6%2Csn-q4fl6ns7&ms=au%2Crdu&mv=m&mvi=1&pl=24&initcwndbps=938750&vprv=1&mime=video%2Fwebm&ns=dzQ4g6pkTsEjvnvwUg8PhYQJ&gir=yes&clen=1495450&dur=246.720&lmt=1573105995337996&mt=1670770639&fvip=5&keepalive=yes&fexp=24001373%2C24007246&c=WEB&txp=1316222&n=Rp0Vrw8keBl_1-3xr&sparams=expire%2Cei%2Cip%2Cid%2Caitags%2Csource%2Crequiressl%2Cvprv%2Cmime%2Cns%2Cgir%2Cclen%2Cdur%2Clmt&lsparams=mh%2Cmm%2Cmn%2Cms%2Cmv%2Cmvi%2Cpl%2Cinitcwndbps&lsig=AG3C_xAwRgIhAIl0ahkexHatApbzKMKeRig-kpSK7412nz0LOnAIgRnCAiEAnA4cl_4-UIy9lPpSeDXlmVczs0Bg7RWw-wWqfJwYMaI%3D&sig=AOq0QJ8wRAIgWB1s6wzHTeJ2QKxmi1YwmW6VU3ttVNIfxhLuIa9ukE8CIGbkKTkBCtf2gtl6pZHyrfyoIPe3SDQPauP0jsNv-RNi", "width": 320, "ext": "webm", "vcodec": "vp9", "acodec": "none", "vbr": 48.49, "downloader_options": {"http_chunk_size": 10485760}, "container": "webm_dash", "format": "242 - 320x240 (240p)", "protocol": "https", "http_headers": {"User-Agent": "Mozilla/5.0 (Windows NT 10.0; Win64; x64) AppleWebKit/537.36 (KHTML, like Gecko) Chrome/72.0.3620.0 Safari/537.36", "Accept-Charset": "ISO-8859-1,utf-8;q=0.7,*;q=0.7", "Accept": "text/html,application/xhtml+xml,application/xml;q=0.9,*/*;q=0.8", "Accept-Encoding": "gzip, deflate", "Accept-Language": "en-us,en;q=0.5"}}, {"asr": null, "filesize": 2342132, "format_id": "243", "format_note": "360p", "fps": 25, "height": 360, "quality": 2, "tbr": 75.944, "url": "https://rr1---sn-0opoxu-ihv6.googlevideo.com/videoplayback?expire=1670792375&ei=V_CVY-GTJs30kgaIy77oAg&ip=189.173.225.87&id=o-ANG1Pd-KLSbUrtYD-H6LMaMC4kR5u3RaRXeLAZHbh5e-&itag=243&aitags=133%2C134%2C135%2C160%2C242%2C243%2C244%2C278&source=youtube&requiressl=yes&mh=XG&mm=31%2C29&mn=sn-0opoxu-ihv6%2Csn-q4fl6ns7&ms=au%2Crdu&mv=m&mvi=1&pl=24&initcwndbps=938750&vprv=1&mime=video%2Fwebm&ns=dzQ4g6pkTsEjvnvwUg8PhYQJ&gir=yes&clen=2342132&dur=246.720&lmt=1573105995337063&mt=1670770639&fvip=5&keepalive=yes&fexp=24001373%2C24007246&c=WEB&txp=1316222&n=Rp0Vrw8keBl_1-3xr&sparams=expire%2Cei%2Cip%2Cid%2Caitags%2Csource%2Crequiressl%2Cvprv%2Cmime%2Cns%2Cgir%2Cclen%2Cdur%2Clmt&lsparams=mh%2Cmm%2Cmn%2Cms%2Cmv%2Cmvi%2Cpl%2Cinitcwndbps&lsig=AG3C_xAwRgIhAOaS4xwq5CMBET-TPQnKDengNdNxRHw3nZQMqoAvwrKBAiEA0UBBJmJpDMGCH9AQ603cLcPfgqhPeKLicpYOnCCvH0A%3D&sig=AOq0QJ8wRAIgZDnO0QCfi5LKUCGSwRKqfVx7h5bWYKc7_6JSMkbSimICIF8ZkDhvrANzuT0ItOJchJ3X0ZnMblwfQH0mTb0lMDg-", "width": 480, "ext": "webm", "vcodec": "vp9", "acodec": "none", "vbr": 75.944, "downloader_options": {"http_chunk_size": 10485760}, "container": "webm_dash", "format": "243 - 480x360 (360p)", "protocol": "https", "http_headers": {"User-Agent": "Mozilla/5.0 (Windows NT 10.0; Win64; x64) AppleWebKit/537.36 (KHTML, like Gecko) Chrome/72.0.3620.0 Safari/537.36", "Accept-Charset": "ISO-8859-1,utf-8;q=0.7,*;q=0.7", "Accept": "text/html,application/xhtml+xml,application/xml;q=0.9,*/*;q=0.8", "Accept-Encoding": "gzip, deflate", "Accept-Language": "en-us,en;q=0.5"}}, {"asr": null, "filesize": 2809989, "format_id": "134", "format_note": "360p", "fps": 25, "height": 360, "quality": 2, "tbr": 91.115, "url": "https://rr1---sn-0opoxu-ihv6.googlevideo.com/videoplayback?expire=1670792375&ei=V_CVY-GTJs30kgaIy77oAg&ip=189.173.225.87&id=o-ANG1Pd-KLSbUrtYD-H6LMaMC4kR5u3RaRXeLAZHbh5e-&itag=134&aitags=133%2C134%2C135%2C160%2C242%2C243%2C244%2C278&source=youtube&requiressl=yes&mh=XG&mm=31%2C29&mn=sn-0opoxu-ihv6%2Csn-q4fl6ns7&ms=au%2Crdu&mv=m&mvi=1&pl=24&initcwndbps=938750&vprv=1&mime=video%2Fmp4&ns=dzQ4g6pkTsEjvnvwUg8PhYQJ&gir=yes&clen=2809989&dur=246.720&lmt=1573105993421691&mt=1670770639&fvip=5&keepalive=yes&fexp=24001373%2C24007246&c=WEB&txp=1316222&n=Rp0Vrw8keBl_1-3xr&sparams=expire%2Cei%2Cip%2Cid%2Caitags%2Csource%2Crequiressl%2Cvprv%2Cmime%2Cns%2Cgir%2Cclen%2Cdur%2Clmt&lsparams=mh%2Cmm%2Cmn%2Cms%2Cmv%2Cmvi%2Cpl%2Cinitcwndbps&lsig=AG3C_xAwRQIhAPWcAr7vsN1e5AYO6gr_bTBBpXDuUgd5yZwT61fWJzUBAiBPmOqndfDBtyn_Bpxsw3yMHMlofXdYnOVwwzgtKVomCw%3D%3D&sig=AOq0QJ8wRAIgR-ojiB26UEL9XqqM1W6MIC25-Pw7i7XXr7XKb0FycdACIEhXCeOeO8sPF5x_UjIVA8BVzLhaN6poz_geDAsefksi", "width": 480, "ext": "mp4", "vcodec": "avc1.4d4015", "acodec": "none", "vbr": 91.115, "downloader_options": {"http_chunk_size": 10485760}, "container": "mp4_dash", "format": "134 - 480x360 (360p)", "protocol": "https", "http_headers": {"User-Agent": "Mozilla/5.0 (Windows NT 10.0; Win64; x64) AppleWebKit/537.36 (KHTML, like Gecko) Chrome/72.0.3620.0 Safari/537.36", "Accept-Charset": "ISO-8859-1,utf-8;q=0.7,*;q=0.7", "Accept": "text/html,application/xhtml+xml,application/xml;q=0.9,*/*;q=0.8", "Accept-Encoding": "gzip, deflate", "Accept-Language": "en-us,en;q=0.5"}}, {"asr": null, "filesize": 3585128, "format_id": "244", "format_note": "480p", "fps": 25, "height": 480, "quality": 3, "tbr": 116.249, "url": "https://rr1---sn-0opoxu-ihv6.googlevideo.com/videoplayback?expire=1670792375&ei=V_CVY-GTJs30kgaIy77oAg&ip=189.173.225.87&id=o-ANG1Pd-KLSbUrtYD-H6LMaMC4kR5u3RaRXeLAZHbh5e-&itag=244&aitags=133%2C134%2C135%2C160%2C242%2C243%2C244%2C278&source=youtube&requiressl=yes&mh=XG&mm=31%2C29&mn=sn-0opoxu-ihv6%2Csn-q4fl6ns7&ms=au%2Crdu&mv=m&mvi=1&pl=24&initcwndbps=938750&vprv=1&mime=video%2Fwebm&ns=dzQ4g6pkTsEjvnvwUg8PhYQJ&gir=yes&clen=3585128&dur=246.720&lmt=1573105995339184&mt=1670770639&fvip=5&keepalive=yes&fexp=24001373%2C24007246&c=WEB&txp=1316222&n=Rp0Vrw8keBl_1-3xr&sparams=expire%2Cei%2Cip%2Cid%2Caitags%2Csource%2Crequiressl%2Cvprv%2Cmime%2Cns%2Cgir%2Cclen%2Cdur%2Clmt&lsparams=mh%2Cmm%2Cmn%2Cms%2Cmv%2Cmvi%2Cpl%2Cinitcwndbps&lsig=AG3C_xAwRgIhAOLSUZXvq7Zw-fFiOxDTvUp-8h9FSFcwMxkdnXOZp2ntAiEAmi8m7Zr5stqc1C_s6xWBhrBbjZSFUah9sgN2vBP2Hhs%3D&sig=AOq0QJ8wRAIgaROv8XMW9527OKkGkA-SqgBAIFOvlXHNjFWxLhK6j3ICIFadVwDK4fcbX0HJF04V7U2kxa7DumdTXA790gBizhC0", "width": 640, "ext": "webm", "vcodec": "vp9", "acodec": "none", "vbr": 116.249, "downloader_options": {"http_chunk_size": 10485760}, "container": "webm_dash", "format": "244 - 640x480 (480p)", "protocol": "https", "http_headers": {"User-Agent": "Mozilla/5.0 (Windows NT 10.0; Win64; x64) AppleWebKit/537.36 (KHTML, like Gecko) Chrome/72.0.3620.0 Safari/537.36", "Accept-Charset": "ISO-8859-1,utf-8;q=0.7,*;q=0.7", "Accept": "text/html,application/xhtml+xml,application/xml;q=0.9,*/*;q=0.8", "Accept-Encoding": "gzip, deflate", "Accept-Language": "en-us,en;q=0.5"}}, {"asr": null, "filesize": 4977657, "format_id": "135", "format_note": "480p", "fps": 25, "height": 480, "quality": 3, "tbr": 161.402, "url": "https://rr1---sn-0opoxu-ihv6.googlevideo.com/videoplayback?expire=1670792375&ei=V_CVY-GTJs30kgaIy77oAg&ip=189.173.225.87&id=o-ANG1Pd-KLSbUrtYD-H6LMaMC4kR5u3RaRXeLAZHbh5e-&itag=135&aitags=133%2C134%2C135%2C160%2C242%2C243%2C244%2C278&source=youtube&requiressl=yes&mh=XG&mm=31%2C29&mn=sn-0opoxu-ihv6%2Csn-q4fl6ns7&ms=au%2Crdu&mv=m&mvi=1&pl=24&initcwndbps=938750&vprv=1&mime=video%2Fmp4&ns=dzQ4g6pkTsEjvnvwUg8PhYQJ&gir=yes&clen=4977657&dur=246.720&lmt=1573105993424074&mt=1670770639&fvip=5&keepalive=yes&fexp=24001373%2C24007246&c=WEB&txp=1316222&n=Rp0Vrw8keBl_1-3xr&sparams=expire%2Cei%2Cip%2Cid%2Caitags%2Csource%2Crequiressl%2Cvprv%2Cmime%2Cns%2Cgir%2Cclen%2Cdur%2Clmt&lsparams=mh%2Cmm%2Cmn%2Cms%2Cmv%2Cmvi%2Cpl%2Cinitcwndbps&lsig=AG3C_xAwRgIhAKm8oSE3XZc-63TILOHGPWo_joAFkafDckIA5S86FqbAAiEAxyCxaHDuDFglH6YpIfeC8xee5U4WgLXp71-QNPtjZgw%3D&sig=AOq0QJ8wRQIhANGBNzC2MMS-ghNmirWXiQtMXFstvkNNwWOv5urEbG-uAiBp8fvegfhblXz5B7KMT66ahr7rtJEPAQJiLq9LgIN-Pg==", "width": 640, "ext": "mp4", "vcodec": "avc1.4d401e", "acodec": "none", "vbr": 161.402, "downloader_options": {"http_chunk_size": 10485760}, "container": "mp4_dash", "format": "135 - 640x480 (480p)", "protocol": "https", "http_headers": {"User-Agent": "Mozilla/5.0 (Windows NT 10.0; Win64; x64) AppleWebKit/537.36 (KHTML, like Gecko) Chrome/72.0.3620.0 Safari/537.36", "Accept-Charset": "ISO-8859-1,utf-8;q=0.7,*;q=0.7", "Accept": "text/html,application/xhtml+xml,application/xml;q=0.9,*/*;q=0.8", "Accept-Encoding": "gzip, deflate", "Accept-Language": "en-us,en;q=0.5"}}, {"asr": 44100, "filesize": null, "format_id": "18", "format_note": "360p", "fps": 25, "height": 360, "quality": 2, "tbr": 219.754, "url": "https://rr1---sn-0opoxu-ihv6.googlevideo.com/videoplayback?expire=1670792375&ei=V_CVY-GTJs30kgaIy77oAg&ip=189.173.225.87&id=o-ANG1Pd-KLSbUrtYD-H6LMaMC4kR5u3RaRXeLAZHbh5e-&itag=18&source=youtube&requiressl=yes&mh=XG&mm=31%2C29&mn=sn-0opoxu-ihv6%2Csn-q4fl6ns7&ms=au%2Crdu&mv=m&mvi=1&pl=24&initcwndbps=938750&vprv=1&mime=video%2Fmp4&ns=HIGERiH3LOXSdTIiFkoKJb0J&cnr=14&ratebypass=yes&dur=246.851&lmt=1658739750017257&mt=1670770639&fvip=5&fexp=24001373%2C24007246&c=WEB&txp=1318224&n=UfhVIkOLu2RReO6HK&sparams=expire%2Cei%2Cip%2Cid%2Citag%2Csource%2Crequiressl%2Cvprv%2Cmime%2Cns%2Ccnr%2Cratebypass%2Cdur%2Clmt&lsparams=mh%2Cmm%2Cmn%2Cms%2Cmv%2Cmvi%2Cpl%2Cinitcwndbps&lsig=AG3C_xAwRAIgQaB42OutB0kdI-27Zne0IlbOUK0YsD8Kvbt0avBEZcoCIBqbp0ZGXQJEgKJM-H1wRNe5PVu7PLaBPvRLmyav3VSG&sig=AOq0QJ8wRAIgGfNOhxAgTEEwQBam5UtcnbDidXPynd8jH6peia2htqICIALTETh1jUZ_qoLBqGiInQpDRrzc5wKxouHznW9lxkXZ", "width": 480, "ext": "mp4", "vcodec": "avc1.42001E", "acodec": "mp4a.40.2", "format": "18 - 480x360 (360p)", "protocol": "https", "http_headers": {"User-Agent": "Mozilla/5.0 (Windows NT 10.0; Win64; x64) AppleWebKit/537.36 (KHTML, like Gecko) Chrome/72.0.3620.0 Safari/537.36", "Accept-Charset": "ISO-8859-1,utf-8;q=0.7,*;q=0.7", "Accept": "text/html,application/xhtml+xml,application/xml;q=0.9,*/*;q=0.8", "Accept-Encoding": "gzip, deflate", "Accept-Language": "en-us,en;q=0.5"}}], "thumbnails": [{"height": 94, "url": "https://i.ytimg.com/vi/ZTpDh-HmwNs/hqdefault.jpg?sqp=-oaymwEbCKgBEF5IVfKriqkDDggBFQAAiEIYAXABwAEG&rs=AOn4CLApoxzdEEhG5VdcN2uzx2TlAD8gzA", "width": 168, "resolution": "168x94", "id": "0"}, {"height": 110, "url": "https://i.ytimg.com/vi/ZTpDh-HmwNs/hqdefault.jpg?sqp=-oaymwEbCMQBEG5IVfKriqkDDggBFQAAiEIYAXABwAEG&rs=AOn4CLD19_GanldoG4AToFgXIuX2oE8JIA", "width": 196, "resolution": "196x110", "id": "1"}, {"height": 138, "url": "https://i.ytimg.com/vi/ZTpDh-HmwNs/hqdefault.jpg?sqp=-oaymwEcCPYBEIoBSFXyq4qpAw4IARUAAIhCGAFwAcABBg==&rs=AOn4CLC2L2pkEkT7KDXrui5Y0e0IYGhVtw", "width": 246, "resolution": "246x138", "id": "2"}, {"height": 188, "url": "https://i.ytimg.com/vi/ZTpDh-HmwNs/hqdefault.jpg?sqp=-oaymwEcCNACELwBSFXyq4qpAw4IARUAAIhCGAFwAcABBg==&rs=AOn4CLBL2eAXdlUgggD6HCMvQbfv0kbRkQ", "width": 336, "resolution": "336x188", "id": "3"}], "description": "Def Con Dos - Veraneo en Puerto Hurraco", "upload_date": "20080622", "uploader": "JossepiBonjourno", "uploader_id": "JossepiBonjourno", "uploader_url": "http://www.youtube.com/user/JossepiBonjourno", "channel_id": "UCTj5eWGcaHUE2Ocvr4WSFHw", "channel_url": "https://www.youtube.com/channel/UCTj5eWGcaHUE2Ocvr4WSFHw", "duration": 247, "view_count": 198719, "average_rating": null, "age_limit": 0, "webpage_url": "https://www.youtube.com/watch?v=ZTpDh-HmwNs", "categories": ["Music"], "tags": ["rap", "metal", "rock", "def", "con", "dos", "veraneo", "puerto", "hurraco"], "is_live": null, "channel": "JossepiBonjourno", "extractor": "youtube", "webpage_url_basename": "watch", "extractor_key": "Youtube", "playlist": null, "playlist_index": null, "thumbnail": "https://i.ytimg.com/vi/ZTpDh-HmwNs/hqdefault.jpg?sqp=-oaymwEcCNACELwBSFXyq4qpAw4IARUAAIhCGAFwAcABBg==&rs=AOn4CLBL2eAXdlUgggD6HCMvQbfv0kbRkQ", "display_id": "ZTpDh-HmwNs", "asr": 44100, "filesize": null, "format_id": "18", "format_note": "360p", "fps": 25, "height": 360, "quality": 2, "tbr": 219.754, "url": "https://rr1---sn-0opoxu-ihv6.googlevideo.com/videoplayback?expire=1670792375&ei=V_CVY-GTJs30kgaIy77oAg&ip=189.173.225.87&id=o-ANG1Pd-KLSbUrtYD-H6LMaMC4kR5u3RaRXeLAZHbh5e-&itag=18&source=youtube&requiressl=yes&mh=XG&mm=31%2C29&mn=sn-0opoxu-ihv6%2Csn-q4fl6ns7&ms=au%2Crdu&mv=m&mvi=1&pl=24&initcwndbps=938750&vprv=1&mime=video%2Fmp4&ns=HIGERiH3LOXSdTIiFkoKJb0J&cnr=14&ratebypass=yes&dur=246.851&lmt=1658739750017257&mt=1670770639&fvip=5&fexp=24001373%2C24007246&c=WEB&txp=1318224&n=UfhVIkOLu2RReO6HK&sparams=expire%2Cei%2Cip%2Cid%2Citag%2Csource%2Crequiressl%2Cvprv%2Cmime%2Cns%2Ccnr%2Cratebypass%2Cdur%2Clmt&lsparams=mh%2Cmm%2Cmn%2Cms%2Cmv%2Cmvi%2Cpl%2Cinitcwndbps&lsig=AG3C_xAwRAIgQaB42OutB0kdI-27Zne0IlbOUK0YsD8Kvbt0avBEZcoCIBqbp0ZGXQJEgKJM-H1wRNe5PVu7PLaBPvRLmyav3VSG&sig=AOq0QJ8wRAIgGfNOhxAgTEEwQBam5UtcnbDidXPynd8jH6peia2htqICIALTETh1jUZ_qoLBqGiInQpDRrzc5wKxouHznW9lxkXZ", "width": 480, "ext": "mp4", "vcodec": "avc1.42001E", "acodec": "mp4a.40.2", "format": "18 - 480x360 (360p)", "protocol": "https", "http_headers": {"User-Agent": "Mozilla/5.0 (Windows NT 10.0; Win64; x64) AppleWebKit/537.36 (KHTML, like Gecko) Chrome/72.0.3620.0 Safari/537.36", "Accept-Charset": "ISO-8859-1,utf-8;q=0.7,*;q=0.7", "Accept": "text/html,application/xhtml+xml,application/xml;q=0.9,*/*;q=0.8", "Accept-Encoding": "gzip, deflate", "Accept-Language": "en-us,en;q=0.5"}, "fulltitle": "Def Con Dos - Veraneo en Puerto Hurraco", "_filename": "Def Con Dos - Veraneo en Puerto Hurraco-ZTpDh-HmwNs.mp4"}